{"stats":{"minecraft:custom":{"minecraft:interact_with_furnace":3,"minecraft:mob_kills":29,"minecraft:interact_with_crafting_table":4,"minecraft:play_one_minute":79698,"minecraft:leave_game":1,"minecraft:time_since_death":74578,"minecraft:sleep_in_bed":2,"minecraft:climb_one_cm":347,"minecraft:time_since_rest":54306,"minecraft:sprint_one_cm":336670,"minecraft:damage_taken":988,"minecraft:walk_one_cm":125860,"minecraft:drop":40,"minecraft:damage_dealt":2856,"minecraft:swim_one_cm":14978,"minecraft:fly_one_cm":476235,"minecraft:open_chest":16,"minecraft:crouch_one_cm":11,"minecraft:deaths":1,"minecraft:sneak_time":198,"minecraft:walk_under_water_one_cm":1531,"minecraft:jump":2151,"minecraft:walk_on_water_one_cm":14109,"minecraft:fall_one_cm":68801},"minecraft:dropped":{"minecraft:sugar_cane":14,"minecraft:wheat_seeds":67,"minecraft:white_bed":1,"minecraft:stick":10,"minecraft:oxeye_daisy":2,"minecraft:mutton":3,"minecraft:fire_charge":1,"minecraft:spider_eye":1,"minecraft:cactus":1,"minecraft:string":2,"minecraft:white_wool":6},"minecraft:mined":{"minecraft:white_bed":1,"minecraft:dark_oak_leaves":7,"minecraft:crafting_table":1,"minecraft:grass_block":5,"minecraft:dead_bush":9,"minecraft:tall_grass":39,"minecraft:spruce_leaves":1,"minecraft:sugar_cane":5,"minecraft:oxeye_daisy":2,"minecraft:hay_block":57,"minecraft:birch_log":1,"minecraft:fire":1,"minecraft:wheat":17,"minecraft:birch_leaves":3,"minecraft:grass":159,"minecraft:oak_log":24,"minecraft:coal_ore":17,"minecraft:sunflower":1,"minecraft:netherrack":9,"minecraft:oak_leaves":13},"minecraft:killed":{"minecraft:pig":5,"minecraft:rabbit":1,"minecraft:spider":1,"minecraft:sheep":17,"minecraft:zombie":1,"minecraft:chicken":1,"minecraft:cow":2},"minecraft:crafted":{"minecraft:wooden_sword":1,"minecraft:oak_planks":96,"minecraft:crafting_table":2,"minecraft:wooden_pickaxe":1,"minecraft:birch_planks":4,"minecraft:bread":176,"minecraft:stick":4,"minecraft:wheat":504},"minecraft:used":{"minecraft:rabbit":1,"minecraft:ender_pearl":1,"minecraft:netherrack":8,"minecraft:white_wool":12,"minecraft:dirt":5,"minecraft:mutton":27,"minecraft:crafting_table":2,"minecraft:diamond_pickaxe":55,"minecraft:apple":1,"minecraft:bread":12,"minecraft:wooden_sword":11,"minecraft:beef":4,"minecraft:porkchop":10,"minecraft:golden_pickaxe":2},"minecraft:picked_up":{"minecraft:birch_log":1,"minecraft:crafting_table":1,"minecraft:iron_chestplate":1,"minecraft:wheat":16,"minecraft:oak_log":24,"minecraft:dirt":5,"minecraft:string":2,"minecraft:iron_leggings":1,"minecraft:apple":1,"minecraft:wheat_seeds":68,"minecraft:beef":4,"minecraft:diamond_helmet":1,"minecraft:rabbit":1,"minecraft:sugar_cane":14,"minecraft:stick":10,"minecraft:porkchop":10,"minecraft:white_bed":1,"minecraft:spider_eye":1,"minecraft:cactus":1,"minecraft:diamond_chestplate":1,"minecraft:diamond_boots":1,"minecraft:hay_block":56,"minecraft:netherrack":8,"minecraft:oxeye_daisy":2,"minecraft:mutton":30,"minecraft:coal":17,"minecraft:diamond_pickaxe":1,"minecraft:white_wool":18,"minecraft:ender_pearl":1}},"DataVersion":2586}